country_module/__init__.py
country_module/country.py
country_module-1.0.1.dist-info/LICENSE
country_module-1.0.1.dist-info/METADATA
country_module-1.0.1.dist-info/WHEEL
country_module-1.0.1.dist-info/top_level.txt
country_module-1.0.1.dist-info/RECORD
