Metadata-Version: 2.1
Name: country-module
Version: 1.0.1
Summary: Python module for country codes with ISO codes.
Home-page: https://github.com/harshildarji/country
Author: Harshil Darji
Author-email: darjiharshil2994@gmail.com
License: UNKNOWN
Platform: UNKNOWN
Classifier: Programming Language :: Python :: 3
Classifier: License :: OSI Approved :: MIT License
Classifier: Operating System :: OS Independent
Requires-Python: >=3.6
